pyramid_signed_params/__init__.py
pyramid_signed_params/interfaces.py
pyramid_signed_params/jwt_signer.py
pyramid_signed_params/tests/__init__.py
pyramid_signed_params/tests/conftest.py
pyramid_signed_params/tests/test_init.py
pyramid_signed_params/tests/test_jwt_signer.py
pyramid_signed_params-1.0.0.dist-info/LICENSE.txt
pyramid_signed_params-1.0.0.dist-info/METADATA
pyramid_signed_params-1.0.0.dist-info/WHEEL
pyramid_signed_params-1.0.0.dist-info/top_level.txt
pyramid_signed_params-1.0.0.dist-info/RECORD
