Metadata-Version: 2.1
Name: pyramid-signed-params
Version: 1.0.0
Summary: Cryptographically signed query parameters for pyramid
Home-page: https://github.com/dairiki/pyramid_signed_params
Author: Jeff Dairiki
Author-email: dairiki@dairiki.org
License: BSD
Keywords: web pyramid cryptography query_string
Platform: UNKNOWN
Classifier: Development Status :: 5 - Production/Stable
Classifier: Framework :: Pyramid
Classifier: Intended Audience :: Developers
Classifier: License :: OSI Approved :: BSD License
Classifier: Topic :: Internet :: WWW/HTTP :: Dynamic Content :: CGI Tools/Libraries
Classifier: Programming Language :: Python :: Implementation :: CPython
Classifier: Programming Language :: Python :: Implementation :: PyPy
Classifier: Programming Language :: Python :: 2.7
Classifier: Programming Language :: Python :: 3
Classifier: Programming Language :: Python :: 3.6
Classifier: Programming Language :: Python :: 3.7
Classifier: Programming Language :: Python :: 3.8
Classifier: Programming Language :: Python :: 3.9
Classifier: Programming Language :: Python :: 3.10
License-File: LICENSE.txt
Requires-Dist: pyjwt (>=1.3)
Requires-Dist: pyramid
Requires-Dist: pyramid-services
Requires-Dist: six
